contigion_indicators/__init__.py
contigion_indicators/bollinger_bands.py
contigion_indicators/candlestick_patterns.py
contigion_indicators/macd.py
contigion_indicators/parabolic_sar.py
contigion_indicators/rsi.py
contigion_indicators/sessions.py
contigion_indicators/sma.py
contigion_indicators/supertrend.py
contigion_indicators/support_and_resistance.py
contigion_indicators/util/__init__.py
contigion_indicators/util/candle_info.py
contigion_indicators/util/functions.py
contigion_indicators/util/metatrader.py
contigion_indicators-1.0.8.dist-info/METADATA
contigion_indicators-1.0.8.dist-info/WHEEL
contigion_indicators-1.0.8.dist-info/top_level.txt
contigion_indicators-1.0.8.dist-info/RECORD
