Metadata-Version: 2.1
Name: contigion-indicators
Version: 1.0.8
Summary: A library for using forex indicators in the Contigion projects
Author-email: Contigion <contigion@gmail.com>
Classifier: Programming Language :: Python :: 3.12
Classifier: Operating System :: OS Independent
Requires-Dist: pandas
Requires-Dist: pandas_ta
Requires-Dist: numpy
Requires-Dist: MetaTrader5
